{
  "lastUpdated": "2026-02-26T15:48:06.638Z",
  "agentCount": 8,
  "activeCollaborations": 0,
  "agents": {
    "aibot": {
      "id": "aibot",
      "name": "AIBot",
      "handle": "@finnyfinny_bot",
      "specialization": "general",
      "status": "unknown",
      "capabilities": [
        "web_search",
        "web_fetch",
        "memory",
        "file_operations",
        "process_management",
        "phone_calls",
        "reminders",
        "bot_delegation",
        "agent_collaboration",
        "goal_management",
        "task_tracking",
        "daily_priorities",
        "market_data",
        "btc_onchain",
        "reddit_sentiment"
      ],
      "lastSeen": "2026-02-26T15:48:06.580Z",
      "lastInteraction": null,
      "interactionCount": 0,
      "notes": "",
      "contactAttempts": [],
      "collaborations": []
    },
    "rolon": {
      "id": "rolon",
      "name": "Rolon",
      "handle": "@rolon2_bot",
      "specialization": "therapy",
      "status": "unknown",
      "capabilities": [
        "web_search",
        "web_fetch",
        "memory",
        "file_operations",
        "process_management",
        "phone_calls",
        "reminders",
        "bot_delegation",
        "agent_collaboration",
        "goal_management",
        "task_tracking",
        "daily_priorities",
        "market_data",
        "btc_onchain",
        "reddit_sentiment"
      ],
      "lastSeen": "2026-02-26T15:48:06.588Z",
      "lastInteraction": null,
      "interactionCount": 0,
      "notes": "",
      "contactAttempts": [],
      "collaborations": []
    },
    "cryptik": {
      "id": "cryptik",
      "name": "cryptik",
      "handle": "@criptikbot",
      "specialization": "crypto",
      "status": "unknown",
      "capabilities": [
        "web_search",
        "web_fetch",
        "memory",
        "file_operations",
        "process_management",
        "phone_calls",
        "reminders",
        "bot_delegation",
        "agent_collaboration",
        "goal_management",
        "task_tracking",
        "daily_priorities",
        "market_data",
        "btc_onchain",
        "reddit_sentiment"
      ],
      "lastSeen": "2026-02-26T15:48:06.597Z",
      "lastInteraction": null,
      "interactionCount": 0,
      "notes": "",
      "contactAttempts": [],
      "collaborations": []
    },
    "jobseeker": {
      "id": "jobseeker",
      "name": "job-seeker",
      "handle": "@jobseeker10bot",
      "specialization": "career",
      "status": "unknown",
      "capabilities": [
        "web_search",
        "web_fetch",
        "memory",
        "file_operations",
        "process_management",
        "phone_calls",
        "reminders",
        "bot_delegation",
        "agent_collaboration",
        "goal_management",
        "task_tracking",
        "daily_priorities",
        "market_data",
        "btc_onchain",
        "reddit_sentiment"
      ],
      "lastSeen": "2026-02-26T15:48:06.605Z",
      "lastInteraction": null,
      "interactionCount": 0,
      "notes": "",
      "contactAttempts": [],
      "collaborations": []
    },
    "myfirstmillion": {
      "id": "myfirstmillion",
      "name": "My First Million",
      "specialization": "entrepreneurship",
      "status": "unknown",
      "capabilities": [
        "web_search",
        "web_fetch",
        "memory",
        "file_operations",
        "process_management",
        "phone_calls",
        "reminders",
        "bot_delegation",
        "agent_collaboration",
        "goal_management",
        "task_tracking",
        "daily_priorities",
        "market_data",
        "btc_onchain",
        "reddit_sentiment"
      ],
      "lastSeen": "2026-02-26T15:48:06.613Z",
      "lastInteraction": null,
      "interactionCount": 0,
      "notes": "",
      "contactAttempts": [],
      "collaborations": []
    },
    "makelifeeasier": {
      "id": "makelifeeasier",
      "name": "make my life easier",
      "specialization": "productivity",
      "status": "unknown",
      "capabilities": [
        "web_search",
        "web_fetch",
        "memory",
        "file_operations",
        "process_management",
        "phone_calls",
        "reminders",
        "bot_delegation",
        "agent_collaboration",
        "goal_management",
        "task_tracking",
        "daily_priorities",
        "market_data",
        "btc_onchain",
        "reddit_sentiment"
      ],
      "lastSeen": "2026-02-26T15:48:06.621Z",
      "lastInteraction": null,
      "interactionCount": 0,
      "notes": "",
      "contactAttempts": [],
      "collaborations": []
    },
    "bookwriter": {
      "id": "bookwriter",
      "name": "bookwriter",
      "specialization": "writing",
      "status": "unknown",
      "capabilities": [
        "web_search",
        "web_fetch",
        "memory",
        "file_operations",
        "process_management",
        "phone_calls",
        "reminders",
        "bot_delegation",
        "agent_collaboration",
        "goal_management",
        "task_tracking",
        "daily_priorities",
        "market_data",
        "btc_onchain",
        "reddit_sentiment"
      ],
      "lastSeen": "2026-02-26T15:48:06.629Z",
      "lastInteraction": null,
      "interactionCount": 0,
      "notes": "",
      "contactAttempts": [],
      "collaborations": []
    },
    "openclone": {
      "id": "openclone",
      "name": "openclone",
      "specialization": "technical",
      "status": "unknown",
      "capabilities": [
        "web_search",
        "web_fetch",
        "memory",
        "file_operations",
        "process_management",
        "phone_calls",
        "reminders",
        "bot_delegation",
        "agent_collaboration",
        "goal_management",
        "task_tracking",
        "daily_priorities",
        "market_data",
        "btc_onchain",
        "reddit_sentiment"
      ],
      "lastSeen": "2026-02-26T15:48:06.638Z",
      "lastInteraction": null,
      "interactionCount": 0,
      "notes": "",
      "contactAttempts": [],
      "collaborations": []
    }
  }
}